{
  "bankId": "route_cheng_quiz",
  "title": "程砚线 题库（课程教学论·被将军也被点醒）",
  "description": "配合 ch_cheng_1/2/3_nodes.json 的反问点拨→马上做题→应用微循环。q_cheng_thinkers_01/q_cheng_curriculum_01(ch1)、q_cheng_design_01/q_cheng_eval_01(ch2)、q_cheng_goodlesson_01(ch3) 为程砚'考问'后的即时检测(knowledgeCheck，刚学完能答对)，同时作章末月考(route_cheng_mock)冷测题。所有选项均为'专业且合理的近似项'(人物-著作-主张/课程模式/三维目标/评价类型/好课标准互为强干扰)，不复习选不对。教学论达标(全部答对)触发 flag cheng_pedagogy_passed，门控 ch3 Good End。",
  "linkedChapter": "route_cheng_3",
  "route": "cheng",
  "errorTypeOptions": ["不会", "记混", "审题", "表达"],
  "scoring": {"single": 2, "multiple": 3, "judge": 8, "short": 10, "material": 18},
  "items": [
    {
      "id": "q_cheng_thinkers_01",
      "type": "single",
      "subject": "302",
      "module": "教育基础知识与基本原理",
      "examPoint": "教育学代表人物与著作、主张的对应（夸美纽斯/赫尔巴特/杜威）",
      "difficulty": "中",
      "stage": "即时",
      "diegetic": {"asker": "cheng", "scene": "meeting_room", "framing": "程砚：先验验你的地基，趁热考你一道"},
      "stem": "某教师设计的一节课，活动一个接一个、强调学生在做中学、几乎不正面讲授，以儿童的兴趣与经验为中心。这种教学取向最接近下列哪位教育家的主张（　）。",
      "options": [
        {"id": "A", "text": "夸美纽斯"},
        {"id": "B", "text": "赫尔巴特"},
        {"id": "C", "text": "杜威"},
        {"id": "D", "text": "苏霍姆林斯基"}
      ],
      "answer": ["C"],
      "explanation": "'做中学、儿童中心、活动中心、经验中心'是杜威(《民主主义与教育》)现代教育思想的核心主张。",
      "distractorTraps": {
        "A": "夸美纽斯著《大教学论》、系统论述班级授课制、使教育学独立(教育学之父)，与'做中学、儿童中心'无关",
        "B": "赫尔巴特主张教师中心、课堂中心、教材中心(传统教育三中心)，与杜威正相反，是现代教育学之父",
        "D": "苏霍姆林斯基主张培养全面和谐发展的人(《把整个心灵献给孩子》)，不是'做中学'"
      },
      "answerKeywords": ["杜威", "做中学", "儿童中心", "现代教育"],
      "source": "教育学人物·与微循环ch1-A(程砚/教育学史)同源，给情境让答案落在杜威(逼真人物辨别)"
    },
    {
      "id": "q_cheng_curriculum_01",
      "type": "single",
      "subject": "302",
      "module": "中学课程",
      "examPoint": "新课改三维目标的辨别（知识与技能/过程与方法/情感态度与价值观）",
      "difficulty": "中",
      "stage": "即时",
      "diegetic": {"asker": "cheng", "scene": "meeting_room", "framing": "程砚：课程是我本行，趁热考你一道"},
      "stem": "某教师在教学目标中写道：'学生能够独立设计并完成一次社会调查问卷。'按新课程改革的三维目标划分，这一条目标属于（　）。",
      "options": [
        {"id": "A", "text": "知识与技能"},
        {"id": "B", "text": "过程与方法"},
        {"id": "C", "text": "情感态度与价值观"},
        {"id": "D", "text": "显性课程目标"}
      ],
      "answer": ["A"],
      "explanation": "'能独立设计并完成问卷'指向'会做什么、形成什么技能'，是结果性的能力，属知识与技能维度。",
      "distractorTraps": {
        "A": null,
        "B": "过程与方法强调'怎么学、在过程中学会什么方法'(如'在合作探究中学会观察比较归纳')，本题强调'能完成、会做'，是技能",
        "C": "情感态度与价值观指向兴趣、态度、价值取向的养成，本题未涉及态度价值的培养",
        "D": "显性/隐性课程是课程类型分类，不是三维目标的维度，属偷换概念"
      },
      "answerKeywords": ["知识与技能", "会做什么", "技能形成", "三维目标"],
      "source": "中学课程·与微循环ch1-C(程砚/课程)同源，换'能设计完成'让答案落在知识与技能(与过程与方法互为强干扰)"
    },
    {
      "id": "q_cheng_design_01",
      "type": "single",
      "subject": "302",
      "module": "中学教学",
      "examPoint": "教学目标的规范表述（行为主体为学生·行为动词可观察可测量）与教学设计ADDIE",
      "difficulty": "中",
      "stage": "即时",
      "diegetic": {"asker": "cheng", "scene": "library", "framing": "程砚：选对了我就承认你有资格谈对错"},
      "stem": "下列四条教学目标的表述中，最规范、最具可评价性的一条是（　）。",
      "options": [
        {"id": "A", "text": "学生能够列举三种细胞器并说出各自的主要功能。"},
        {"id": "B", "text": "使学生掌握细胞器的相关知识。"},
        {"id": "C", "text": "通过本节课，让学生充分感受生命的奥妙与美好。"},
        {"id": "D", "text": "认真讲解细胞器的结构，组织一次小组讨论。"}
      ],
      "answer": ["A"],
      "explanation": "规范教学目标三要素：行为主体是'学生'、行为动词可观察可测量(列举、说出)、内容具体。A 项三者俱全。",
      "distractorTraps": {
        "A": null,
        "B": "'使学生'主体实为教师，'掌握'笼统不可测，是最常见的虚写目标",
        "C": "'充分感受'不可观察评价；情感态度目标也须落到可见行为",
        "D": "陈述的是'教师要做的活动'而非'学生要达到的目标'，把教学过程当成了目标"
      },
      "answerKeywords": ["行为主体学生", "可观察行为动词", "目标三要素", "可评价"],
      "source": "教学设计·与微循环ch2-A(程砚/教学设计ADDIE)同源，考目标规范表述(与'主体错位/不可测/活动当目标'互为强干扰)"
    },
    {
      "id": "q_cheng_eval_01",
      "type": "single",
      "subject": "302",
      "module": "中学教学",
      "examPoint": "教学评价的类型（诊断性/形成性/总结性·相对/绝对评价）",
      "difficulty": "中",
      "stage": "即时",
      "diegetic": {"asker": "cheng", "scene": "library", "framing": "程砚：省得你将来被一句'数据'唬住，趁热考你一道"},
      "stem": "一位教师在单元教学过程中，通过随堂小测、提问与课堂观察持续了解学生掌握情况，并据此及时调整后续教学。这种评价属于（　）。",
      "options": [
        {"id": "A", "text": "诊断性评价"},
        {"id": "B", "text": "形成性评价"},
        {"id": "C", "text": "总结性评价"},
        {"id": "D", "text": "相对评价"}
      ],
      "answer": ["B"],
      "explanation": "'教学过程中持续反馈、据以及时调整教学'是形成性评价的核心——为改进而评，不为定论而评。",
      "distractorTraps": {
        "A": "诊断性评价在'教学前'摸底、了解起点，与题干'过程中持续了解'时机不符",
        "B": null,
        "C": "总结性评价在'教学后'下结论(如期末考、定成绩)，与题干时机不符",
        "D": "相对评价是按'参照标准'(常模排名次)分类，本题考的是按'时机功能'分的诊断/形成/总结，分类维度不同"
      },
      "answerKeywords": ["形成性评价", "过程中反馈", "及时调整教学", "为改进而评"],
      "source": "教学评价·与微循环ch2-C(程砚/教学评价)同源，给情境让答案落在形成性评价(与诊断/总结/相对互为强干扰)"
    },
    {
      "id": "q_cheng_goodlesson_01",
      "type": "single",
      "subject": "302",
      "module": "中学教学",
      "examPoint": "好课的评价标准（以学生发展为本·目标达成与学生主体）与说课评课",
      "difficulty": "中",
      "stage": "即时",
      "diegetic": {"asker": "cheng", "scene": "meeting_room", "framing": "程砚：答对了我才放心让你上台"},
      "stem": "评价一堂课是否是'好课'，最根本的落脚点应当是（　）。",
      "options": [
        {"id": "A", "text": "教学目标是否达成、学生是否真正参与并有实质收获"},
        {"id": "B", "text": "教师讲授是否流畅精彩、教态与语言是否优雅生动"},
        {"id": "C", "text": "课堂气氛是否热闹、活动数量是否多、有没有掌声"},
        {"id": "D", "text": "本堂课对应的考试平均分与排名等数据是否好看"}
      ],
      "answer": ["A"],
      "explanation": "好课的根本落脚点是'以学生发展为本'——看目标达成与学生真实的参与收获，而非教师表演、形式热闹或唯分数。",
      "distractorTraps": {
        "A": null,
        "B": "教师表现是手段而非目的，只看老师讲得好是'教师中心'的老路",
        "C": "热闹≠有效，活动须指向目标、学生思维须被真正激活('有目标的热闹才叫课')",
        "D": "分数只是结果之一，'好看数据'易导向相对评价与应试表演，非好课的根本标准"
      },
      "answerKeywords": ["目标达成", "学生主体", "以学生发展为本", "评课落脚点"],
      "source": "好课标准·与微循环ch3(程砚/好课标准)同源，考评课最根本落脚点(与教师中心/形式热闹/唯分数互为强干扰)；全卷答对触发 cheng_pedagogy_passed"
    }
  ],
  "mockExam": {
    "id": "route_cheng_mock",
    "title": "程砚线 月考（冷测·检验留存）",
    "framing": "程砚用一连串反问把你将到根上的考点——教育学人物、三维目标、教学设计与目标规范、教学评价类型、好课标准，隔天不带点拨再考一遍，这次才看你真站得住没。全部答对则判定'教学论达标'(cheng_pedagogy_passed)，是 ch3 告白 Good End 的门槛之一。",
    "coldTestItems": ["q_cheng_thinkers_01", "q_cheng_curriculum_01", "q_cheng_design_01", "q_cheng_eval_01", "q_cheng_goodlesson_01"],
    "note": "冷测换新情境、考辨别：杜威vs其余人物、知识与技能vs其余三维、规范目标vs主体错位/活动当目标、形成性vs诊断/总结/相对、以学生发展为本vs教师中心/形式热闹/唯分数。",
    "passFlag": "cheng_pedagogy_passed",
    "weaknessThreshold": "某 module 答错即标薄弱，触发程砚私教重讲(人物-著作对应/三维目标/教学设计目标规范/评价类型/好课标准)；教学论未达标则 ch3 末 branch 走不到 Good End。"
  }
}
